phianonymizer/__init__.py
phianonymizer-0.0.6.dist-info/LICENSE
phianonymizer-0.0.6.dist-info/METADATA
phianonymizer-0.0.6.dist-info/WHEEL
phianonymizer-0.0.6.dist-info/top_level.txt
phianonymizer-0.0.6.dist-info/RECORD
