Metadata-Version: 2.2
Name: phianonymizer
Version: 0.0.6
Summary: A tool to anonymize data before sending to LLM providers, then re-identify the data after receiving the response.
Author: Josh XT
Author-email: josh@devxt.com
Requires-Python: >=3.10
License-File: LICENSE
Requires-Dist: llama-cpp-python
Requires-Dist: cryptography
Requires-Dist: huggingface-hub
Dynamic: author
Dynamic: author-email
Dynamic: description
Dynamic: description-content-type
Dynamic: requires-dist
Dynamic: requires-python
Dynamic: summary
